README.txt
bootstrap.py
buildout.cfg
setup.cfg
setup.py
bise/__init__.py
bise.ecosystemservices.egg-info/PKG-INFO
bise.ecosystemservices.egg-info/SOURCES.txt
bise.ecosystemservices.egg-info/dependency_links.txt
bise.ecosystemservices.egg-info/entry_points.txt
bise.ecosystemservices.egg-info/namespace_packages.txt
bise.ecosystemservices.egg-info/not-zip-safe
bise.ecosystemservices.egg-info/paster_plugins.txt
bise.ecosystemservices.egg-info/requires.txt
bise.ecosystemservices.egg-info/top_level.txt
bise/ecosystemservices/INTEGRATION.txt
bise/ecosystemservices/__init__.py
bise/ecosystemservices/configure.zcml
bise/ecosystemservices/ecosystem.py
bise/ecosystemservices/permissions.zcml
bise/ecosystemservices/service.py
bise/ecosystemservices/study.py
bise/ecosystemservices/tests.py
bise/ecosystemservices/browser/__init__.py
bise/ecosystemservices/browser/atlasview.py
bise/ecosystemservices/browser/configure.zcml
bise/ecosystemservices/browser/maesgalleryview.py
bise/ecosystemservices/browser/templates/atlasview.pt
bise/ecosystemservices/browser/templates/maesgalleryview.pt
bise/ecosystemservices/locales/README.txt
bise/ecosystemservices/profiles/default/cssregistry.xml
bise/ecosystemservices/profiles/default/diff_tool.xml
bise/ecosystemservices/profiles/default/jsregistry.xml
bise/ecosystemservices/profiles/default/metadata.xml
bise/ecosystemservices/profiles/default/rolemap.xml
bise/ecosystemservices/profiles/default/types.xml
bise/ecosystemservices/profiles/default/types/Ecosystem.xml
bise/ecosystemservices/profiles/default/types/Folder.xml
bise/ecosystemservices/profiles/default/types/FolderishPage.xml
bise/ecosystemservices/profiles/default/types/Service.xml
bise/ecosystemservices/profiles/default/types/Study.xml
bise/ecosystemservices/static/glyphicons-halflings-white.png
bise/ecosystemservices/static/maes.css
bise/ecosystemservices/static/maes.js
bise/ecosystemservices/static/maesGallery.css
bise/ecosystemservices/static/maesGallery.js
bise/ecosystemservices/static/owl.carousel.css
bise/ecosystemservices/static/owl.carousel.min.js
bise/ecosystemservices/static/owl.theme.css
bise/ecosystemservices/templates/README.txt
bise/ecosystemservices/templates/ecosystemview.pt
bise/ecosystemservices/templates/serviceview.pt
bise/ecosystemservices/templates/studyview.pt
docs/HISTORY.txt
docs/INSTALL.txt
docs/LICENSE.GPL
docs/LICENSE.txt