Metadata-Version: 1.1
Name: bise.ecosystemservices
Version: 1.0.1
Summary: Ecosystem Services Maps
Home-page: https://github.com/eea/bise.ecosystemservices
Author: Mikel Larreategi
Author-email: mlarreategi@codesyntax.com
License: GPL
Platform: UNKNOWN
Classifier: Framework :: Plone
Classifier: Programming Language :: Python
Classifier: Topic :: Software Development :: Libraries :: Python Modules
